{
  "annotations": {
    "list": [
      {
        "builtIn": 1,
        "datasource": {
          "type": "grafana",
          "uid": "-- Grafana --"
        },
        "enable": true,
        "hide": true,
        "iconColor": "rgba(0, 211, 255, 1)",
        "name": "Annotations & Alerts",
        "type": "dashboard"
      }
    ]
  },
  "editable": true,
  "fiscalYearStartMonth": 0,
  "graphTooltip": 0,
  "id": 4,
  "links": [],
  "panels": [
    {
      "collapsed": false,
      "gridPos": {
        "h": 1,
        "w": 24,
        "x": 0,
        "y": 0
      },
      "id": 17,
      "panels": [],
      "title": "Full Cluster Summary",
      "type": "row"
    },
    {
      "datasource": {
        "type": "prometheus"
      },
      "description": "Number of distinct build versions present across all instances in the cluster. This will be 2 when an upgrade is in progress.",
      "fieldConfig": {
        "defaults": {
          "color": {
            "mode": "thresholds"
          },
          "decimals": 0,
          "mappings": [],
          "thresholds": {
            "mode": "absolute",
            "steps": [
              {
                "color": "green",
                "value": 0
              },
              {
                "color": "yellow",
                "value": 2
              },
              {
                "color": "red",
                "value": 3
              }
            ]
          },
          "unit": "short"
        },
        "overrides": []
      },
      "gridPos": {
        "h": 3,
        "w": 8,
        "x": 0,
        "y": 1
      },
      "id": 15,
      "options": {
        "colorMode": "background",
        "graphMode": "none",
        "justifyMode": "center",
        "orientation": "horizontal",
        "percentChangeColorMode": "standard",
        "reduceOptions": {
          "calcs": [
            "lastNotNull"
          ],
          "fields": "",
          "values": false
        },
        "showPercentChange": false,
        "textMode": "value",
        "wideLayout": true
      },
      "pluginVersion": "12.3.1",
      "targets": [
        {
          "datasource": {
            "type": "prometheus"
          },
          "editorMode": "code",
          "expr": "count(count by (version) (ozone_build_info))",
          "instant": true,
          "legendFormat": "",
          "range": false,
          "refId": "A"
        }
      ],
      "title": "Active Versions",
      "type": "stat"
    },
    {
      "datasource": {
        "type": "prometheus"
      },
      "description": "Indicates whether all instances in the cluster have been finalized.",
      "fieldConfig": {
        "defaults": {
          "color": {
            "mode": "thresholds"
          },
          "mappings": [
            {
              "options": {
                "0": {
                  "color": "yellow",
                  "index": 0,
                  "text": "No"
                },
                "1": {
                  "color": "green",
                  "index": 1,
                  "text": "Yes"
                }
              },
              "type": "value"
            }
          ],
          "thresholds": {
            "mode": "absolute",
            "steps": [
              {
                "color": "red",
                "value": 0
              },
              {
                "color": "green",
                "value": 1
              }
            ]
          }
        },
        "overrides": []
      },
      "gridPos": {
        "h": 3,
        "w": 8,
        "x": 8,
        "y": 1
      },
      "id": 14,
      "options": {
        "colorMode": "background",
        "graphMode": "none",
        "justifyMode": "center",
        "orientation": "horizontal",
        "percentChangeColorMode": "standard",
        "reduceOptions": {
          "calcs": [
            "lastNotNull"
          ],
          "fields": "",
          "values": false
        },
        "showPercentChange": false,
        "textMode": "value",
        "wideLayout": true
      },
      "pluginVersion": "12.3.1",
      "targets": [
        {
          "datasource": {
            "type": "prometheus"
          },
          "editorMode": "code",
          "expr": "(count(component_version_manager_metrics_software_version * on(instance) group_left() (ozone_build_info{component!~\"recon\"})) - sum((component_version_manager_metrics_software_version == bool component_version_manager_metrics_apparent_version) * on(instance) group_left() (ozone_build_info{component!~\"recon\"}))) == bool 0",
          "instant": true,
          "legendFormat": "",
          "range": false,
          "refId": "A"
        }
      ],
      "title": "Cluster Finalized?",
      "type": "stat"
    },
    {
      "datasource": {
        "type": "prometheus"
      },
      "description": "Number of instances currently hidden by the component and instance selectors at the top of the dashboard. 0 means all nodes are visible.",
      "fieldConfig": {
        "defaults": {
          "color": {
            "mode": "thresholds"
          },
          "decimals": 0,
          "mappings": [],
          "thresholds": {
            "mode": "absolute",
            "steps": [
              {
                "color": "green",
                "value": 0
              },
              {
                "color": "red",
                "value": 1
              }
            ]
          },
          "unit": "short"
        },
        "overrides": []
      },
      "gridPos": {
        "h": 3,
        "w": 8,
        "x": 16,
        "y": 1
      },
      "id": 16,
      "options": {
        "colorMode": "background",
        "graphMode": "none",
        "justifyMode": "center",
        "orientation": "horizontal",
        "percentChangeColorMode": "standard",
        "reduceOptions": {
          "calcs": [
            "lastNotNull"
          ],
          "fields": "",
          "values": false
        },
        "showPercentChange": false,
        "textMode": "value",
        "wideLayout": true
      },
      "pluginVersion": "12.3.1",
      "targets": [
        {
          "datasource": {
            "type": "prometheus"
          },
          "editorMode": "code",
          "expr": "count(ozone_build_info) - count(ozone_build_info{component=~\"$component\",instance=~\"$instance\"})",
          "instant": true,
          "legendFormat": "",
          "range": false,
          "refId": "A"
        }
      ],
      "title": "Nodes Hidden by Selector",
      "type": "stat"
    },
    {
      "collapsed": false,
      "gridPos": {
        "h": 1,
        "w": 24,
        "x": 0,
        "y": 4
      },
      "id": 4,
      "panels": [],
      "title": "Versions",
      "type": "row"
    },
    {
      "datasource": {
        "type": "prometheus"
      },
      "description": "Total number of selected instances running each version. The chart fills with a single slice when the upgrade completes.",
      "fieldConfig": {
        "defaults": {
          "color": {
            "fixedColor": "#354c6f",
            "mode": "palette-classic"
          },
          "custom": {
            "hideFrom": {
              "legend": false,
              "tooltip": false,
              "viz": false
            }
          },
          "decimals": 0,
          "displayName": "${__field.labels.version}",
          "mappings": [],
          "unit": "short"
        },
        "overrides": []
      },
      "gridPos": {
        "h": 9,
        "w": 9,
        "x": 0,
        "y": 5
      },
      "id": 2,
      "options": {
        "displayLabels": [
          "name"
        ],
        "legend": {
          "calcs": [],
          "displayMode": "table",
          "placement": "right",
          "showLegend": true,
          "values": [
            "value",
            "percent"
          ]
        },
        "pieType": "pie",
        "reduceOptions": {
          "calcs": [
            "lastNotNull"
          ],
          "fields": "",
          "values": false
        },
        "sort": "desc",
        "tooltip": {
          "hideZeros": false,
          "mode": "single",
          "sort": "none"
        }
      },
      "pluginVersion": "12.3.1",
      "targets": [
        {
          "datasource": {
            "type": "prometheus"
          },
          "editorMode": "code",
          "expr": "count by (version) (ozone_build_info{component=~\"$component\",instance=~\"$instance\"})",
          "instant": true,
          "legendFormat": "{{version}}",
          "range": false,
          "refId": "A"
        }
      ],
      "title": "Instances Per Version",
      "type": "piechart"
    },
    {
      "datasource": {
        "type": "prometheus"
      },
      "description": "Build version of each selected instance. Use this to see which instances still need to be upgraded.",
      "fieldConfig": {
        "defaults": {
          "color": {
            "mode": "thresholds"
          },
          "custom": {
            "align": "auto",
            "cellOptions": {
              "type": "auto"
            },
            "footer": {
              "reducers": []
            },
            "inspect": false
          },
          "mappings": [],
          "thresholds": {
            "mode": "absolute",
            "steps": [
              {
                "color": "green",
                "value": 0
              }
            ]
          }
        },
        "overrides": []
      },
      "gridPos": {
        "h": 9,
        "w": 14,
        "x": 9,
        "y": 5
      },
      "id": 5,
      "options": {
        "cellHeight": "sm",
        "footer": {
          "countRows": false,
          "enablePagination": true,
          "fields": "",
          "reducer": [
            "sum"
          ],
          "show": false
        },
        "showHeader": true,
        "sortBy": [
          {
            "desc": false,
            "displayName": "version"
          }
        ]
      },
      "pluginVersion": "12.3.1",
      "targets": [
        {
          "datasource": {
            "type": "prometheus"
          },
          "editorMode": "code",
          "expr": "ozone_build_info{instance=~\"$instance\"}",
          "format": "table",
          "instant": true,
          "refId": "A"
        }
      ],
      "title": "Versions",
      "transformations": [
        {
          "id": "organize",
          "options": {
            "excludeByName": {
              "Time": true,
              "Value": true,
              "__name__": true,
              "context": true,
              "exported_component": true,
              "hostname": true,
              "job": true,
              "revision": true
            },
            "indexByName": {
              "component": 1,
              "instance": 0,
              "version": 2
            },
            "renameByName": {}
          }
        }
      ],
      "type": "table"
    },
    {
      "datasource": {
        "type": "prometheus"
      },
      "description": "Total number of selected instances running each build version over time.",
      "fieldConfig": {
        "defaults": {
          "color": {
            "mode": "palette-classic"
          },
          "custom": {
            "axisBorderShow": false,
            "axisCenteredZero": false,
            "axisColorMode": "text",
            "axisLabel": "Instances",
            "axisPlacement": "auto",
            "barAlignment": 0,
            "barWidthFactor": 0.6,
            "drawStyle": "line",
            "fillOpacity": 10,
            "gradientMode": "none",
            "hideFrom": {
              "legend": false,
              "tooltip": false,
              "viz": false
            },
            "insertNulls": false,
            "lineInterpolation": "stepAfter",
            "lineWidth": 2,
            "pointSize": 5,
            "scaleDistribution": {
              "type": "linear"
            },
            "showPoints": "auto",
            "showValues": false,
            "spanNulls": false,
            "stacking": {
              "group": "A",
              "mode": "none"
            },
            "thresholdsStyle": {
              "mode": "off"
            }
          },
          "decimals": 0,
          "mappings": [],
          "min": 0,
          "thresholds": {
            "mode": "absolute",
            "steps": [
              {
                "color": "green",
                "value": 0
              }
            ]
          },
          "unit": "short"
        },
        "overrides": []
      },
      "gridPos": {
        "h": 9,
        "w": 23,
        "x": 0,
        "y": 14
      },
      "id": 6,
      "options": {
        "legend": {
          "calcs": [],
          "displayMode": "list",
          "placement": "bottom",
          "showLegend": true
        },
        "tooltip": {
          "hideZeros": false,
          "mode": "multi",
          "sort": "none"
        }
      },
      "pluginVersion": "12.3.1",
      "targets": [
        {
          "datasource": {
            "type": "prometheus"
          },
          "editorMode": "code",
          "expr": "count by (version) (ozone_build_info{instance=~\"$instance\"})",
          "legendFormat": "{{version}}",
          "range": true,
          "refId": "A"
        }
      ],
      "title": "Instances Per Version Over Time",
      "type": "timeseries"
    },
    {
      "collapsed": false,
      "gridPos": {
        "h": 1,
        "w": 24,
        "x": 0,
        "y": 23
      },
      "id": 9,
      "panels": [],
      "title": "Finalization Status",
      "type": "row"
    },
    {
      "datasource": {
        "type": "prometheus"
      },
      "description": "Total number of selected instances which have finalized. Recon and S3 gateway are excluded.",
      "fieldConfig": {
        "defaults": {
          "color": {
            "mode": "palette-classic"
          },
          "custom": {
            "hideFrom": {
              "legend": false,
              "tooltip": false,
              "viz": false
            }
          },
          "decimals": 0,
          "mappings": [],
          "unit": "short"
        },
        "overrides": [
          {
            "matcher": {
              "id": "byName",
              "options": "finalized"
            },
            "properties": [
              {
                "id": "color",
                "value": {
                  "fixedColor": "green",
                  "mode": "fixed"
                }
              }
            ]
          },
          {
            "matcher": {
              "id": "byName",
              "options": "unfinalized"
            },
            "properties": [
              {
                "id": "color",
                "value": {
                  "fixedColor": "semi-dark-yellow",
                  "mode": "fixed"
                }
              }
            ]
          }
        ]
      },
      "gridPos": {
        "h": 8,
        "w": 9,
        "x": 0,
        "y": 24
      },
      "id": 3,
      "options": {
        "displayLabels": [
          "name"
        ],
        "legend": {
          "calcs": [],
          "displayMode": "table",
          "placement": "right",
          "showLegend": true,
          "values": [
            "value",
            "percent"
          ]
        },
        "pieType": "pie",
        "reduceOptions": {
          "calcs": [
            "lastNotNull"
          ],
          "fields": "",
          "values": false
        },
        "sort": "desc",
        "tooltip": {
          "hideZeros": false,
          "mode": "single",
          "sort": "none"
        }
      },
      "pluginVersion": "12.3.1",
      "targets": [
        {
          "datasource": {
            "type": "prometheus"
          },
          "editorMode": "code",
          "expr": "sum((component_version_manager_metrics_software_version{instance=~\"$instance\"} == bool component_version_manager_metrics_apparent_version{instance=~\"$instance\"}) * on(instance) group_left() (ozone_build_info{component!~\"recon\"}))",
          "instant": true,
          "legendFormat": "finalized",
          "range": false,
          "refId": "A"
        },
        {
          "datasource": {
            "type": "prometheus"
          },
          "editorMode": "code",
          "expr": "count(component_version_manager_metrics_software_version{instance=~\"$instance\"} * on(instance) group_left() (ozone_build_info{component!~\"recon\"})) - sum((component_version_manager_metrics_software_version{instance=~\"$instance\"} == bool component_version_manager_metrics_apparent_version{instance=~\"$instance\"}) * on(instance) group_left() (ozone_build_info{component!~\"recon\"}))",
          "instant": true,
          "legendFormat": "unfinalized",
          "range": false,
          "refId": "B"
        }
      ],
      "title": "Finalized vs Total Instances",
      "type": "piechart"
    },
    {
      "datasource": {
        "type": "prometheus"
      },
      "description": "Finalization status of each selected instance. All instances except S3 Gateway and Recon finalize automatically when a finalize command is given.",
      "fieldConfig": {
        "defaults": {
          "color": {
            "mode": "thresholds"
          },
          "custom": {
            "align": "auto",
            "cellOptions": {
              "type": "auto"
            },
            "footer": {
              "reducers": []
            },
            "inspect": false
          },
          "mappings": [],
          "thresholds": {
            "mode": "absolute",
            "steps": [
              {
                "color": "green",
                "value": 0
              }
            ]
          }
        },
        "overrides": [
          {
            "matcher": {
              "id": "byName",
              "options": "Finalized?"
            },
            "properties": [
              {
                "id": "custom.cellOptions",
                "value": {
                  "type": "color-text"
                }
              },
              {
                "id": "mappings",
                "value": [
                  {
                    "options": {
                      "0": {
                        "color": "red",
                        "index": 0,
                        "text": "false"
                      },
                      "1": {
                        "color": "green",
                        "index": 1,
                        "text": "true"
                      }
                    },
                    "type": "value"
                  }
                ]
              },
              {
                "id": "custom.width",
                "value": 244
              }
            ]
          },
          {
            "matcher": {
              "id": "byName",
              "options": "Software Version"
            },
            "properties": [
              {
                "id": "custom.width",
                "value": 226
              }
            ]
          },
          {
            "matcher": {
              "id": "byName",
              "options": "Instance"
            },
            "properties": [
              {
                "id": "custom.width",
                "value": 631
              }
            ]
          },
          {
            "matcher": {
              "id": "byName",
              "options": "Apparent Version"
            },
            "properties": [
              {
                "id": "custom.width",
                "value": 439
              }
            ]
          }
        ]
      },
      "gridPos": {
        "h": 8,
        "w": 14,
        "x": 9,
        "y": 24
      },
      "id": 10,
      "options": {
        "cellHeight": "sm",
        "footer": {
          "countRows": false,
          "enablePagination": true,
          "fields": "",
          "reducer": [
            "sum"
          ],
          "show": false
        },
        "showHeader": true,
        "sortBy": [
          {
            "desc": true,
            "displayName": "Finalized?"
          }
        ]
      },
      "pluginVersion": "12.3.1",
      "targets": [
        {
          "datasource": {
            "type": "prometheus"
          },
          "editorMode": "code",
          "expr": "(component_version_manager_metrics_software_version{instance=~\"$instance\"} == bool component_version_manager_metrics_apparent_version{instance=~\"$instance\"}) * on(instance) group_left() (ozone_build_info{component!~\"recon\"})",
          "format": "table",
          "instant": true,
          "refId": "A"
        }
      ],
      "title": "Finalized Instances",
      "transformations": [
        {
          "id": "organize",
          "options": {
            "excludeByName": {
              "Time": true,
              "__name__": true,
              "component": true,
              "context": true,
              "exported_component": true,
              "hostname": true,
              "job": true,
              "revision": true,
              "version": true
            },
            "indexByName": {
              "Finalized?": 1,
              "Instance": 0
            },
            "renameByName": {
              "Value": "Finalized?",
              "instance": "Instance"
            }
          }
        }
      ],
      "type": "table"
    },
    {
      "datasource": {
        "type": "prometheus"
      },
      "description": "Number of selected instances which have finalized over time (green), stacked with the number still pending finalization (yellow). The top of the stack is the total eligible instance count.",
      "fieldConfig": {
        "defaults": {
          "color": {
            "mode": "palette-classic"
          },
          "custom": {
            "axisBorderShow": false,
            "axisCenteredZero": false,
            "axisColorMode": "text",
            "axisLabel": "Instances",
            "axisPlacement": "auto",
            "barAlignment": 0,
            "barWidthFactor": 0.6,
            "drawStyle": "line",
            "fillOpacity": 10,
            "gradientMode": "none",
            "hideFrom": {
              "legend": false,
              "tooltip": false,
              "viz": false
            },
            "insertNulls": false,
            "lineInterpolation": "stepAfter",
            "lineWidth": 2,
            "pointSize": 5,
            "scaleDistribution": {
              "type": "linear"
            },
            "showPoints": "auto",
            "showValues": false,
            "spanNulls": false,
            "stacking": {
              "group": "A",
              "mode": "none"
            },
            "thresholdsStyle": {
              "mode": "off"
            }
          },
          "decimals": 0,
          "mappings": [],
          "min": 0,
          "thresholds": {
            "mode": "absolute",
            "steps": [
              {
                "color": "green",
                "value": 0
              }
            ]
          },
          "unit": "short"
        },
        "overrides": [
          {
            "matcher": {
              "id": "byName",
              "options": "finalized"
            },
            "properties": [
              {
                "id": "color",
                "value": {
                  "fixedColor": "green",
                  "mode": "fixed"
                }
              },
              {
                "id": "custom.fillOpacity",
                "value": 25
              },
              {
                "id": "custom.stacking",
                "value": {
                  "group": "A",
                  "mode": "normal"
                }
              }
            ]
          },
          {
            "matcher": {
              "id": "byName",
              "options": "remaining"
            },
            "properties": [
              {
                "id": "color",
                "value": {
                  "fixedColor": "yellow",
                  "mode": "fixed"
                }
              },
              {
                "id": "custom.fillOpacity",
                "value": 25
              },
              {
                "id": "custom.lineWidth",
                "value": 0
              },
              {
                "id": "custom.showPoints",
                "value": "never"
              },
              {
                "id": "custom.stacking",
                "value": {
                  "group": "A",
                  "mode": "normal"
                }
              },
              {
                "id": "custom.hideFrom",
                "value": {
                  "legend": false,
                  "tooltip": false,
                  "viz": false
                }
              }
            ]
          }
        ]
      },
      "gridPos": {
        "h": 9,
        "w": 23,
        "x": 0,
        "y": 32
      },
      "id": 11,
      "options": {
        "legend": {
          "calcs": [],
          "displayMode": "list",
          "placement": "bottom",
          "showLegend": true
        },
        "tooltip": {
          "hideZeros": false,
          "mode": "multi",
          "sort": "none"
        }
      },
      "pluginVersion": "12.3.1",
      "targets": [
        {
          "datasource": {
            "type": "prometheus"
          },
          "editorMode": "code",
          "expr": "count(((component_version_manager_metrics_software_version{instance=~\"$instance\"} == bool component_version_manager_metrics_apparent_version{instance=~\"$instance\"}) * on(instance) group_left() (ozone_build_info{component!~\"recon\"})) == 1) or vector(0)",
          "legendFormat": "finalized",
          "range": true,
          "refId": "A"
        },
        {
          "datasource": {
            "type": "prometheus"
          },
          "editorMode": "code",
          "expr": "count(component_version_manager_metrics_software_version{instance=~\"$instance\"} * on(instance) group_left() (ozone_build_info{component!~\"recon\"})) - (count(((component_version_manager_metrics_software_version{instance=~\"$instance\"} == bool component_version_manager_metrics_apparent_version{instance=~\"$instance\"}) * on(instance) group_left() (ozone_build_info{component!~\"recon\"})) == 1) or vector(0))",
          "legendFormat": "remaining",
          "range": true,
          "refId": "C"
        }
      ],
      "title": "Finalized vs Total Instances Over Time",
      "type": "timeseries"
    }
  ],
  "preload": false,
  "refresh": "30s",
  "schemaVersion": 42,
  "tags": [
    "ozone",
    "upgrade"
  ],
  "templating": {
    "list": [
      {
        "current": {
          "text": "All",
          "value": "$__all"
        },
        "datasource": {
          "type": "prometheus"
        },
        "definition": "label_values(ozone_build_info, component)",
        "includeAll": true,
        "label": "component",
        "multi": true,
        "name": "component",
        "options": [],
        "query": {
          "query": "label_values(ozone_build_info, component)",
          "refId": "StandardVariableQuery"
        },
        "refresh": 1,
        "regex": "",
        "sort": 1,
        "type": "query"
      },
      {
        "current": {
          "text": "All",
          "value": "$__all"
        },
        "datasource": {
          "type": "prometheus"
        },
        "definition": "label_values(ozone_build_info{component=~\"$component\"}, instance)",
        "includeAll": true,
        "label": "instance",
        "multi": true,
        "name": "instance",
        "options": [],
        "query": {
          "query": "label_values(ozone_build_info{component=~\"$component\"}, instance)",
          "refId": "StandardVariableQuery"
        },
        "refresh": 1,
        "regex": "",
        "sort": 1,
        "type": "query"
      },
      {
        "baseFilters": [],
        "datasource": {
          "type": "prometheus"
        },
        "filters": [],
        "name": "Filters",
        "type": "adhoc"
      }
    ]
  },
  "time": {
    "from": "now-30m",
    "to": "now"
  },
  "timepicker": {},
  "timezone": "",
  "title": "Ozone - Rolling Upgrade",
  "uid": "ozone-rolling-upgrade",
  "version": 3
}
